Workbook

Sheet Pending payments 
A1: Revenue Sumarry | B1: Jan | C1: Feb | D1: March | E1: April | F1: May | G1: June | H1: July | I1: Aug | J1: Sep | K1: Oct | L1: Nov | M1: Dec | N1: Total
A2: Gross Rev Before GST | B2: ='JAN 25'!H32 -> 56144 | C2: ='FEB 25'!I33 -> 37168 | D2: ='March 25'!G32 -> 131137 | E2: ='April 25 '!G33 -> 208715 | F2: ='May 25'!G24 -> 229200 | G2: ='June 25'!G26 -> 77420 | N2: =SUM(B2:M2) -> 739784
A3: Discount | B3: ='JAN 25'!I32 -> 5476.4 | C3: ='FEB 25'!J33 -> 5874 | D3: ='March 25'!I32 -> 11563.25 | E3: ='April 25 '!I33 -> 19575 | F3: ='May 25'!I24 -> 13810 | G3: ='June 25'!I26 -> 9522 | N3: =SUM(B3:M3) -> 65820.65 | O3: =N3/N2 -> 0.088972795
A4: Rev Rent | B4: =B2-B3 -> 50667.6 | C4: =C2-C3 -> 31294 | D4: =D2-D3 -> 119573.75 | E4: =E2-E3 -> 189140 | F4: =F2-F3 -> 215390 | G4: =G2-G3 -> 67898 | N4: =SUM(B4:M4) -> 673963.35
A5: Rev Breakage | B5: ='JAN 25'!G32 -> 16170 | C5: ='FEB 25'!H33 -> 1260 | D5: ='March 25'!H32 -> 10564 | E5: ='April 25 '!H33 -> 23445 | F5: ='May 25'!H24 -> 18470 | G5: ='June 25'!H26 -> 1 | N5: =SUM(B5:M5) -> 69910
A6: Total Rev before GST | B6: =B4+B5 -> 66837.6 | C6: =C4+C5 -> 32554 | D6: =D4+D5 -> 130137.75 | E6: =E4+E5 -> 212585 | F6: =F4+F5 -> 233860 | G6: =G4+G5 -> 67899 | N6: =SUM(B6:M6) -> 743873.35
A7: GST | B7: ='JAN 25'!K32 -> 11024.568 | C7: =C6*18% -> 5859.72 | D7: =D6*18% -> 23424.795 | E7: ='April 25 '!K33 -> 37905.3 | F7: ='May 25'!K24 -> 42094.8 | G7: ='June 25'!K26 -> 12977.64 | N7: =SUM(B7:M7) -> 133286.82
A8: Gross Rev | B8: =B6+B7 -> 77862.168 | C8: =C6+C7 -> 38413.72 | D8: =D6+D7 -> 153562.54 | E8: =E6+E7 -> 250490.3 | F8: =SUM(F6:F7) -> 275954.8 | G8: =G6+G7 -> 80876.64 | N8: =SUM(B8:M8) -> 877160.17
A10: Pending Payments
A11: Company | B11: Jan | C11: Feb | D11: March | E11: April | F11: May | G11: June | H11: July | I11: Aug | J11: Sep | K11: Oct | L11: Nov | M11: Dec | N11: Total
A12: Foodies Hospitality | B12: 0 | C12: 0 | D12: 0 | E12: 0 | F12: ='May 25'!N9 -> 28992.6 | G12: 0 | H12: 0 | I12: 0 | J12: 0 | K12: 0 | L12: 0 | M12: 0 | N12: =SUM(B12:M12) -> 28992.6
A13: Naksha | B13: 0 | C13: 0 | D13: 0 | E13: 0 | F13: 0 | G13: 0 | H13: 0 | I13: 0 | J13: 0 | K13: 0 | L13: 0 | M13: 0 | N13: =SUM(B13:M13) -> 0
A14: Elior Hospitality | B14: 0 | C14: 0 | D14: 0 | E14: 0 | F14: ='May 25'!N4+'May 25'!N7 -> 91261.2 | G14: 0 | H14: 0 | I14: 0 | J14: 0 | K14: 0 | L14: 0 | M14: 0 | N14: =SUM(B14:M14) -> 91261.2
A15: GRITTY FOODWORKS PRIVATE LIMITED | B15: 0 | C15: 0 | D15: 0 | E15: 0 | F15: ='May 25'!L11 -> 35400 | G15: 0 | H15: 0 | I15: 0 | J15: 0 | K15: 0 | L15: 0 | M15: 0 | N15: =SUM(B15:M15) -> 35400
A16: sage and Olio | B16: 0 | C16: 0 | D16: 0 | E16: 0 | F16: 0 | G16: ='June 25'!N3 -> 30208 | H16: 0 | I16: 0 | J16: 0 | K16: 0 | L16: 0 | M16: 0 | N16: =SUM(B16:M16) -> 30208
A17: Otra Restaurant | B17: 0 | C17: 0 | D17: 0 | E17: 0 | F17: 0 | G17: ='June 25'!N2 -> 32140.84 | H17: 0 | I17: 0 | J17: 0 | K17: 0 | L17: 0 | M17: 0 | N17: =SUM(B17:M17) -> 32140.84
A18: Pooja Herimath | G18: ='June 25'!N6 -> 0
A19: Iteeha Hospitality | B19: 0 | C19: 0 | D19: 0 | E19: 0 | F19: ='June 25'!N4 -> 10620 | G19: 0 | H19: 0 | I19: 0 | J19: 0 | K19: 0 | L19: 0 | M19: 0 | N19: =SUM(B19:M19) -> 10620
A20: Sage and Saffron | B20: 0 | C20: 0 | D20: 0 | E20: 0 | F20: ='May 25'!N10 -> 26809.6 | G20: 0 | H20: 0 | I20: 0 | J20: 0 | K20: 0 | L20: 0 | M20: 0 | N20: =SUM(B20:M20) -> 26809.6
A21: Total | B21: =SUM(B12:B20) -> 0 | C21: =SUM(C12:C20) -> 0 | D21: =SUM(D12:D20) -> 0 | E21: =SUM(E12:E20) -> 0 | F21: =SUM(F12:F20) -> 193083.4 | G21: =SUM(G12:G20) -> 62348.84 | H21: =SUM(H12:H20) -> 0 | I21: =SUM(I12:I20) -> 0 | ... M21: =SUM(M12:M20) -> 0 | N21: =SUM(B21:M21) -> 255432.24 | O21: =N21/N6 -> 0.34338136

Sheet JAN 25
A2: Sr No | B2: Company/Client Name | C2: GST Number | D2: Contact Detail | E2: Invoice no | F2: Date | G2: Rev Breakage | H2: Rental value | I2: Discount on Rent | J2: Total Rev | K2: GST 18% | L2: Gross Revenue | M2: Payment Pending | N2: Payment Type | O2: Purchase unit value | P2: ROI %
A3: 1 | B3: Natasha Mehta | D3: 9820628870 | E3: 1 | F3: 7th Jan | G3: 0 | H3: 2125 | I3: 0 | J3: =G3+H3-I3 -> 2125 | K3: =J3*18% -> 382.5 | L3: =J3+K3 -> 2507.5 | M3: 0 | N3: cash | O3: 21040 | P3: =J3/O3 -> 0.1009981
A4: 2 | B4: Irfan Pabaney | D4: 9820151040 | E4: 2 | F4: 11th Jan | G4: 0 | H4: 2040 | I4: 0 | J4: =G4+H4-I4 -> 2040 | K4: =J4*18% -> 367.2 | L4: =J4+K4 -> 2407.2 | M4: 0 | N4: In Account | O4: 12600 | P4: =J4/O4 -> 0.16190476
A5: 3 | B5: Ms Khayal /Americano | D5: 8928890965 | E5: 3 | F5: 15th Jan | G5: 0 | H5: 3840 | I5: 0 | J5: =G5+H5-I5 -> 3840 | K5: =J5*18% -> 691.2 | L5: =J5+K5 -> 4531.2 | M5: 0 | N5: In Account | O5: 25800 | P5: =J5/O5 -> 0.14883721
A6: 4 | B6: Bar Baraati | C6: 27AKXPP5257F1ZH | D6: 9004696778 | E6: 4 | F6: 20th Jan | G6: 0 | H6: 4500 | I6: 0 | J6: =G6+H6-I6 -> 4500 | K6: 0 | L6: =J6+K6 -> 4500 | M6: 0 | N6: cash | O6: 36000 | P6: =J6/O6 -> 0.125
B7: Bar Baraati | C7: 27AKXPP5257F1ZH | D7: 9004696778 | G7: 1090 | H7: 0 | I7: 0 | J7: =G7+H7-I7 -> 1090 | K7: 0 | L7: =J7+K7 -> 1090 | M7: 0 | N7: cash
A8: 5 | B8: Rohan Timblo | D8: 9820882211 | E8: 5 | F8: 22nd Jan | G8: 0 | H8: 1824 | I8: =H8*10% -> 182.4 | J8: =G8+H8-I8 -> 1641.6 | K8: =J8*18% -> 295.488 | L8: =J8+K8 -> 1937.088 | M8: 0 | N8: In Account | O8: 14160 | P8: =J8/O8 -> 0.1159322
A9: 6 | B9: Sage & Saffon | C9: 27ADUFS8750Q1ZQ | D9: 9867384572 | E9: 6 | F9: 23rd Jan | G9: 0 | H9: =(19500)+(48*45) -> 21660 | I9: 1000 | J9: =G9+H9-I9 -> 20660 | K9: =J9*18% -> 3718.8 | L9: =J9+K9 -> 24378.8 | M9: 0 | N9: In Account | O9: 137280 | P9: =J9/O9 -> 0.15049534
A10: 8 | B10: Sage & Saffon | C10: 27ADUFS8750Q1ZQ | D10: 9867384572 | E10: 8 | F10: 25th Jan | G10: 14130 | H10: 0 | I10: 1413 | J10: =G10+H10-I10 -> 12717 | K10: =J10*18% -> 2289.06 | L10: =J10+K10 -> 15006.06 | M10: 0 | N10: In Account
A11: 7 | B11: Rohan Timblo | E11: 7 | F11: 25th Jan | G11: 0 | H11: 19205 | I11: 2881 | J11: =G11+H11-I11 -> 16324 | K11: =J11*18% -> 2938.32 | L11: =J11+K11 -> 19262.32 | M11: 0 | N11: In Account | O11: 125754 | P11: =J11/O11 -> 0.12980899
A12: 9 | B12: Rohan Timblo | D12: 9820882211 | E12: 7 | F12: 25th Jan | G12: 950 | H12: 950 | I12: 0 | J12: =G12+H12-I12 -> 1900 | K12: =J12*18% -> 342 | L12: =J12+K12 -> 2242 | M12: 0 | N12: In Account
A13: 10 | J13: =G13+H13-I13 -> 0 | K13: =J13*18% -> 0 | L13: =J13+K13 -> 0
A14: 11 | J14: =G14+H14-I14 -> 0 | K14: =J14*18% -> 0 | L14: =J14+K14 -> 0
A15: 12 | J15: =G15+H15-I15 -> 0 | K15: =J15*18% -> 0 | L15: =J15+K15 -> 0
A16: 13 | J16: =G16+H16-I16 -> 0 | K16: =J16*18% -> 0 | L16: =J16+K16 -> 0
A17: 14 | J17: =G17+H17-I17 -> 0 | K17: =J17*18% -> 0 | L17: =J17+K17 -> 0
A18: 15 | J18: =G18+H18-I18 -> 0 | K18: =J18*18% -> 0 | L18: =J18+K18 -> 0
A19: 16 | J19: =G19+H19-I19 -> 0 | K19: =J19*18% -> 0 | L19: =J19+K19 -> 0
A20: 17 | J20: =G20+H20-I20 -> 0 | K20: =J20*18% -> 0 | L20: =J20+K20 -> 0
A21: 18 | J21: =G21+H21-I21 -> 0 | K21: =J21*18% -> 0 | L21: =J21+K21 -> 0
A22: 19 | J22: =G22+H22-I22 -> 0 | K22: =J22*18% -> 0 | L22: =J22+K22 -> 0
A23: 20 | J23: =G23+H23-I23 -> 0 | K23: =J23*18% -> 0 | L23: =J23+K23 -> 0
A24: 21 | J24: =G24+H24-I24 -> 0 | K24: =J24*18% -> 0 | L24: =J24+K24 -> 0
... A31: 28 | J31: =G31+H31-I31 -> 0 | K31: =J31*18% -> 0 | L31: =J31+K31 -> 0
G32: =SUM(G3:G31) -> 16170 | H32: =SUM(H3:H31) -> 56144 | I32: =SUM(I3:I31) -> 5476.4 | J32: =SUM(J3:J31) -> 66837.6 | K32: =SUM(K3:K31) -> 11024.568 | L32: =SUM(L3:L31) -> 77862.168 | M32: =SUM(M3:M31) -> 0 | O32: =SUM(O3:O31) -> 372634 | P32: =J32/O32 -> 0.17936528
I33: =I32/J32 -> 0.081935916

Sheet FEB 25
A2: Sr No | B2: Company/Client Name | C2: Comments | D2: GST Number | E2: Contact Detail | F2: Invoice no | G2: Date | H2: Breakage | I2: Rent | J2: Discount | K2: Total Rev | L2: GST 18% | M2: Gross Revenue | N2: Advance Payment | O2: Payment Pending | P2: Payment Type | Q2: Purchase unit value | R2: ROI %
A3: 1 | B3: Rohan Timblo | C3: Higher Discount | E3: 9820882211 | F3: 9 | G3: 1st | H3: 0 | I3: 12830 | J3: 3230 | K3: =H3+I3-J3 -> 9600 | L3: =K3*18% -> 1728 | M3: =K3+L3 -> 11328 | O3: 0 | P3: Corp Account | Q3: 118790 | R3: =K3/Q3 -> 0.080814883
A4: 2 | B4: Samir | E4: 9820167690 | F4: 10 | G4: 1st | H4: 1260 | I4: 0 | J4: 60 | K4: =H4+I4-J4 -> 1200 | L4: =K4*18% -> 216 | M4: =K4+L4 -> 1416 | O4: 0 | P4: Corp Account | Q4: =H4 -> 1260 | R4: =K4/Q4 -> 0.95238095
A5: 3 | B5: Amal (Sage and olio) | D5: 27ADUFS8750Q1ZQ | E5: 9821561159 | F5: 11 | G5: 15th | H5: 0 | I5: 3258 | J5: 0 | K5: =H5+I5-J5 -> 3258 | L5: =K5*18% -> 586.44 | M5: =K5+L5 -> 3844.44 | O5: 0 | P5: Corp Account | Q5: 28940 | R5: =M5/Q5 -> 0.13284174
A6: 4 | B6: Bar Barati | D6: 27AKXPP5257F1ZH | E6: 9004696778 | F6: 12 | G6: 28th Feb to 2nd Mar | H6: 0 | I6: 9800 | J6: 0 | K6: =H6+I6-J6 -> 9800 | L6: =K6*18% -> 1764 | M6: =K6+L6 -> 11564 | N6: 0 | O6: 0 | P6: Corp Account | Q6: =250*100 -> 25000 | R6: =K6/Q6 -> 0.392
A7: 5 | B7: Sapna Bajaj | D7: 27AAEFP4977H1ZT | E7: 9821163571 | F7: 13 | G7: 21st Feb | H7: 0 | I7: 4200 | J7: 2400 | K7: =H7+I7-J7 -> 1800 | L7: =K7*18% -> 324 | M7: =K7+L7 -> 2124 | O7: 0 | P7: Corp Account | Q7: =2500*12 -> 30000 | R7: =K7/Q7 -> 0.06
A8: 6 | B8: Samantha Noroaha | E8: 9892059186 | F8: 14 | G8: 21st Feb | H8: 0 | I8: 850 | J8: 0 | K8: =H8+I8-J8 -> 850 | L8: =K8*18% -> 153 | M8: =K8+L8 -> 1003 | P8: Corp Account | Q8: 9415 | R8: =K8/Q8 -> 0.090281466
A9: 7 | B9: Eat Drink Design | D9: 27AACCE9284F1ZE | E9: 9552525257 | F9: 15 | G9: 27th Feb | H9: 0 | I9: 2630 | J9: 184 | K9: =H9+I9-J9 -> 2446 | L9: =K9*18% -> 440.28 | M9: =K9+L9 -> 2886.28 | N9: 0 | O9: 0 | P9: Corp Account | Q9: 32400 | R9: =K9/Q9 -> 0.075493827
A10: 8 | B10: Natasha Mehta | E10: 9820628870 | F10: 16 | G10: 25th Feb | H10: 0 | I10: 1000 | J10: 0 | K10: =H10+I10-J10 -> 1000 | L10: =K10*18% -> 180 | M10: =K10+L10 -> 1180 | O10: 0 | P10: Corp Account | Q10: =1500*3 -> 4500 | R10: =K10/Q10 -> 0.22222222
A11: 9 | B11: We are Wholesum | D11: 27AADFW6639C1Z2 | F11: 17 | G11: 27th Feb | H11: 0 | I11: 2600 | J11: 0 | K11: =H11+I11-J11 -> 2600 | L11: =K11*18% -> 468 | M11: =K11+L11 -> 3068 | O11: 0
K12: =H12+I12-J12 -> 0
K13: =H13+I13-J13 -> 0
K14: =H14+I14-J14 -> 0
K15: =H15+I15-J15 -> 0 | L15: =K15*18% -> 0 | M15: =K15+L15 -> 0
K16: =H16+I16-J16 -> 0 | L16: =K16*18% -> 0 | M16: =K16+L16 -> 0
K17: =H17+I17-J17 -> 0 | L17: =K17*18% -> 0 | M17: =K17+L17 -> 0
K18: =H18+I18-J18 -> 0 | L18: =K18*18% -> 0 | M18: =K18+L18 -> 0
K19: =H19+I19-J19 -> 0 | L19: =K19*18% -> 0 | M19: =K19+L19 -> 0
K20: =H20+I20-J20 -> 0 | L20: =K20*18% -> 0 | M20: =K20+L20 -> 0
K21: =H21+I21-J21 -> 0 | L21: =K21*18% -> 0 | M21: =K21+L21 -> 0
K22: =H22+I22-J22 -> 0 | L22: =K22*18% -> 0 | M22: =K22+L22 -> 0
K23: =H23+I23-J23 -> 0 | L23: =K23*18% -> 0 | M23: =K23+L23 -> 0
K24: =H24+I24-J24 -> 0 | L24: =K24*18% -> 0 | M24: =K24+L24 -> 0
K25: =H25+I25-J25 -> 0 | L25: =K25*18% -> 0 | M25: =K25+L25 -> 0
K26: =H26+I26-J26 -> 0 | L26: =K26*18% -> 0 | M26: =K26+L26 -> 0
... K32: =H32+I32-J32 -> 0 | L32: =K32*18% -> 0 | M32: =K32+L32 -> 0
H33: =SUM(H3:H32) -> 1260 | I33: =SUM(I3:I32) -> 37168 | J33: =SUM(J3:J32) -> 5874 | K33: =SUM(K3:K32) -> 32554 | L33: =SUM(L3:L32) -> 5859.72 | M33: =SUM(M3:M32) -> 38413.72 | N33: =SUM(N3:N32) -> 0 | O33: =SUM(O3:O32) -> 0 | Q33: =SUM(Q3:Q32) -> 250305 | R33: =K33/Q33 -> 0.13005733
J34: =J33/I33 -> 0.15803917

Sheet March 25
A1: Sr No | B1: Company/Client Name | C1: GST Number | D1: Contact Detail | E1: Invoice no | F1: Date | G1: Rent Rev | H1: Breakage | I1: Discount on Rent | J1: Net Rev | K1: GST 18% | L1: Gross Rev | M1: Payment Recived | N1: Payment Pending | O1: Payment Type | P1: Purchase unit value | Q1: ROI %
A2: 1 | B2: Amal (Sage and olio) | C2: 27ADUFS8750Q1ZQ | D2: 9821561159 | E2: 18 | F2: 7th March | G2: 10610 | H2: 0 | I2: 1600 | J2: =G2+H2-I2 -> 9010 | K2: =J2*18% -> 1621.8 | L2: =J2+K2 -> 10631.8 | M2: =L2 -> 10631.8 | N2: 0 | O2: Corp Account | P2: 71620 | Q2: =J2/P2 -> 0.12580285
A3: 2 | B3: Mg Street | C3: 27AABCF4192L1ZC | D3: 8698547390 | E3: 19 | F3: 2nd & 3rd March | G3: =(9560*2) -> 19120 | H3: =(250*15) -> 3750 | I3: 0 | J3: =G3+H3-I3 -> 22870 | K3: =J3*18% -> 4116.6 | L3: =J3+K3 -> 26986.6 | M3: =L3 -> 26986.6 | N3: 0 | O3: Corp Account | P3: 82300 | Q3: =J3/P3 -> 0.27788578
A4: 3 | B4: Rohan timblo | D4: 9820882211 | E4: 20 | F4: 6th March | G4: 3470 | H4: 0 | I4: 374 | J4: =G4+H4-I4 -> 3096 | K4: =J4*18% -> 557.28 | L4: =J4+K4 -> 3653.28 | M4: =L4 -> 3653.28 | N4: =L4-M4 -> 0 | O4: Corp Account | P4: 24101 | Q4: =J4/P4 -> 0.1284594
A5: 4 | B5: Samir | D5: 9820167690 | E5: 21 | F5: 5th March | G5: 0 | H5: 1500 | I5: 375 | J5: =G5+H5-I5 -> 1125 | K5: =J5*18% -> 202.5 | L5: =J5+K5 -> 1327.5 | M5: =L5 -> 1327.5 | N5: 0 | O5: Corp Account | P5: 1500 | Q5: =J5/P5 -> 0.75
A6: 5 | B6: Mg Street | C6: 27AABCF4192L1ZC | D6: 8698547390 | E6: 22 | F6: 10th March | G6: 3808 | H6: 4100 | I6: 1142 | J6: =G6+H6-I6 -> 6766 | K6: =J6*18% -> 1217.88 | L6: =J6+K6 -> 7983.88 | M6: =L6 -> 7983.88 | N6: 0 | O6: Corp Account | P6: =H6 -> 4100 | Q6: =I6/P6 -> 0.27853659
A7: 6 | B7: Rohan timblo | D7: 9820882211 | E7: 23 | F7: 17th March | G7: 42244 | H7: 0 | I7: 3000 | J7: =G7+H7-I7 -> 39244 | K7: =J7*18% -> 7063.92 | L7: =J7+K7 -> 46307.92 | M7: =L7 -> 46307.92 | N7: =L7-M7 -> 0 | O7: Corp Account | P7: 282950 | Q7: =J7/P7 -> 0.13869588
A8: 7 | B8: Eat Drink Design | C8: 27AACCE9284F1ZE | D8: 9552525257 | E8: 24 | F8: 12th March | G8: 600 | H8: 0 | I8: 0 | J8: =G8+H8-I8 -> 600 | K8: =J8*18% -> 108 | L8: =J8+K8 -> 708 | M8: 708 | N8: =L8-M8 -> 0 | O8: Corp Account | P8: =(235*30) -> 7050 | Q8: =J8/P8 -> 0.085106383
A9: 8 | B9: Zene Hospitality | C9: 27AACCZ2784R1ZD | D9: 9820442210 | E9: 25 | F9: 16th March | G9: 23670 | H9: 350 | I9: 3551 | J9: =G9+H9-I9 -> 20469 | K9: =J9*18% -> 3684.42 | L9: =J9+K9 -> 24153.42 | M9: =15000+9153 -> 24153 | N9: 0 | O9: Corp Account | P9: 95350 | Q9: =J9/P9 -> 0.21467226
A10: 9 | B10: Nine Hospitality | C10: 27AARFN8911G1ZU | D10: 9930586351 | E10: 26 | F10: 22nd March | G10: 5250 | I10: 368 | J10: =G10+H10-I10 -> 4882 | K10: =J10*18% -> 878.76 | L10: =J10+K10 -> 5760.76 | M10: 5761 | N10: 0 | O10: Corp Account | P10: 42500 | Q10: =J10/P10 -> 0.11487059
A11: 10 | B11: Naksha Firoz | C11: 27AAKCC4172E1ZP | D11: 9820198472 | E11: 27 | F11: 22nd March | G11: 10065 | H11: 0 | I11: =G11*5% -> 503.25 | J11: =G11+H11-I11 -> 9561.75 | K11: =J11*18% -> 1721.115 | L11: =J11+K11 -> 11282.865 | M11: =L11 -> 11282.865 | N11: =L11-M11 -> 0 | O11: Corp Account | P11: 80000 | Q11: =J11/P11 -> 0.11952187
A12: 11 | B12: Sapna Bajaj | C12: 27AAEFP4977H1ZT | D12: 9821163571 | E12: 28 | F12: 25th March | G12: 1500 | I12: 0 | J12: =G12+H12-I12 -> 1500 | K12: =J12*18% -> 270 | L12: =J12+K12 -> 1770 | M12: 1770 | N12: =L12-M12 -> 0 | O12: Corp Account | P12: =500*25 -> 12500 | Q12: =J12/P12 -> 0.12
A13: 12 | B13: Nine Hospitality | C13: 27AARFN8911G1ZU | E13: 29 | F13: 26th March | G13: 2600 | I13: 150 | J13: =G13+H13-I13 -> 2450 | K13: =J13*18% -> 441 | L13: =J13+K13 -> 2891 | M13: 2891 | N13: =L13-M13 -> 0 | O13: Corp Account | P13: =(250*40)+(235*40) -> 19400 | Q13: =J13/P13 -> 0.12628866
A14: 13 | B14: Foodies Hospitality LLP | C14: 27AAEFF1696H1Z9 | E14: 30 | F14: 26th March | G14: 8200 | I14: 500 | J14: =G14+H14-I14 -> 7700 | K14: =J14*18% -> 1386 | L14: =J14+K14 -> 9086 | M14: =L14 -> 9086 | N14: =L14-M14 -> 0 | O14: Corp Account | P14: 64170 | Q14: =J14/P14 -> 0.11999377
A15: 14 | B15: Samir | E15: 31 | F15: 26th March | G15: 0 | H15: 864 | I15: 0 | J15: =H15-I15 -> 864 | K15: =J15*18% -> 155.52 | L15: =SUM(J15:K15) -> 1019.52 | M15: =L15 -> 1019.52 | O15: personal | P15: 1000 | Q15: =J15/P15 -> 0.864
G32: =SUM(G2:G31) -> 131137 | H32: =SUM(H2:H31) -> 10564 | I32: =SUM(I2:I31) -> 11563.25 | J32: =G32+H32-I32 -> 130137.75 | K32: =SUM(K2:K31) -> 23424.795 | L32: =SUM(L2:L31) -> 153562.54 | M32: =SUM(M2:M31) -> 153562.36 | N32: =SUM(N2:N31) -> 0 | P32: =SUM(P2:P31) -> 788541 | Q32: =J32/P32 -> 0.16503612
I33: =I32/G32 -> 0.088176868

Sheet April 25 
A1: Sr No | B1: Company/Client Name | C1: GST Number | D1: Contact Detail | E1: Invoice no | F1: Date | G1: Rent Rev | H1: Breakage | I1: Discount on Rent | J1: Net Rev | K1: GST 18% | L1: Gross Rev | M1: Payment Recived | N1: Payment Pending | O1: Payment Type | P1: Purchase unit value | Q1: ROI %
A2: 1 | B2: Amal (Sage and olio) | C2: 27ADUFS8750Q1ZQ | D2: 9821561159 | E2: 32 | F2: 1st April | G2: 40000 | H2: 5665 | I2: 8000 | J2: =G2+H2-I2 -> 37665 | K2: =J2*18% -> 6779.7 | L2: =J2+K2 -> 44444.7 | M2: =L2 -> 44444.7 | N2: =L2-M2 -> 0 | O2: Corporate account | P2: 313750 | Q2: =J2/P2 -> 0.12004781
A3: 2 | B3: Naksha Firoz | C3: 27AAKCC4172E1ZP | E3: 34 | F3: 5th April | G3: 5700 | H3: =5210+2000 -> 7210 | I3: 0 | J3: =G3+H3-I3 -> 12910 | K3: =(J3*18%)-360 -> 1963.8 | L3: =J3+K3 -> 14873.8 | M3: =L3 -> 14873.8 | N3: =L3-M3 -> 0 | O3: Corporate account | P3: =(1200*2)+(15600)+(1800*4)+(1500+2500+2000)+(2500+3000+3000)+2000 -> 41700 | Q3: =J3/P3 -> 0.30959233
A4: 3 | B4: Elior Gokul | C4: 27AAGFE2060C1ZY | E4: 33 | F4: 12th April | G4: 15870 | H4: 0 | I4: 0 | J4: =G4+H4-I4 -> 15870 | K4: =J4*18% -> 2856.6 | L4: =J4+K4 -> 18726.6 | M4: =L4 -> 18726.6 | N4: 0 | O4: Corporate account | P4: 114800 | Q4: =J4/P4 -> 0.13824042
A5: 3 | B5: Elior Gokul | C5: 27AAGFE2060C1ZY | E5: 33 | F5: 24th and 25th April | G5: 59920 | H5: =3000+(100)+(100)+(200)+(200)+(1800) -> 5400 | I5: 0 | J5: =G5+H5-I5 -> 65320 | K5: =J5*18% -> 11757.6 | L5: =J5+K5 -> 77077.6 | M5: 77078 | N5: =L5-M5 -> -0.4 | O5: Corporate account | P5: 158600 | Q5: =J5/P5 -> 0.41185372
A6: 4 | B6: Nine | C6: 27AARFN8911G1ZU | E6: 35 | F6: 12th April | G6: 3250 | I6: 325 | J6: =G6+H6-I6 -> 2925 | K6: =J6*18% -> 526.5 | L6: =J6+K6 -> 3451.5 | M6: =L6 -> 3451.5 | N6: 0 | O6: Corporate account | P6: =(15000*5)+(1000*5) -> 80000 | Q6: =J6/P6 -> 0.0365625
A7: 5 | B7: Mag street | C7: 27AABCF4192L1ZC | E7: 36 | F7: 12th April | G7: 320 | J7: =G7+H7-I7 -> 320 | K7: =J7*18% -> 57.6 | L7: =J7+K7 -> 377.6 | M7: =L7 -> 377.6 | N7: 0 | O7: Corporate account | P7: 3600 | Q7: =J7/P7 -> 0.088888889
A8: 6 | B8: Amal (Sage and olio) | C8: 27ADUFS8750Q1ZQ | E8: 37 | F8: 27th April | G8: 18780 | H8: 1600 | I8: 3750 | J8: =G8+H8-I8 -> 16630 | K8: =J8*18% -> 2993.4 | L8: =J8+K8 -> 19623.4 | M8: =L8 -> 19623.4 | N8: 0 | O8: Corporate account | P8: 163250 | Q8: =J8/P8 -> 0.1018683
A9: 7 | B9: Yolo (Naveen) | C9: 27AABFY6348J1ZP | E9: 38 | F9: 18th April | G9: 1000 | J9: =G9+H9-I9 -> 1000 | K9: =J9*18% -> 180 | L9: =J9+K9 -> 1180 | M9: =L9 -> 1180 | O9: Corporate account | P9: 18800 | Q9: =J9/P9 -> 0.053191489
A10: 8 | B10: Rohan Timblo | E10: 39 | F10: 24th April | G10: 23525 | I10: 2000 | J10: =G10+H10-I10 -> 21525 | K10: =J10*18% -> 3874.5 | L10: =J10+K10 -> 25399.5 | M10: =L10 -> 25399.5 | N10: 0 | O10: Corporate account | P10: 146550 | Q10: =J10/P10 -> 0.1468782
A11: 9 | B11: Amal (Sage and olio) | C11: 27ADUFS8750Q1ZQ | E11: 40 | F11: 27th April | G11: =27860+720 -> 28580 | H11: 3570 | I11: 5000 | J11: =G11+H11-I11 -> 27150 | K11: =J11*18% -> 4887 | L11: =J11+K11 -> 32037 | M11: =L11 -> 32037 | N11: 0 | O11: Corporate account | P11: 200550 | Q11: =J11/P11 -> 0.13537771
A12: 10 | B12: Soma | C12: 27BNXPP8213P1ZV | E12: 41 | F12: 28th April | G12: 9670 | I12: 500 | J12: =G12+H12-I12 -> 9170 | K12: =J12*18% -> 1650.6 | L12: =J12+K12 -> 10820.6 | M12: =L12 -> 10820.6 | N12: 0 | O12: Corporate account | P12: 50450 | Q12: =J12/P12 -> 0.18176412
A13: 11 | B13: Nesco | C13: 27AAACN1222E1Z3 | E13: 42 | F13: 28th April | G13: 2100 | I13: 0 | J13: =G13+H13-I13 -> 2100 | K13: =J13*18% -> 378 | L13: =J13+K13 -> 2478 | M13: =L13 -> 2478 | N13: 0 | O13: Corporate account | P13: =2500*6 -> 15000 | Q13: =J13/P13 -> 0.14
G33: =SUM(G2:G32) -> 208715 | H33: =SUM(H2:H32) -> 23445 | I33: =SUM(I2:I32) -> 19575 | J33: =SUM(J2:J32) -> 212585 | K33: =SUM(K2:K32) -> 37905.3 | L33: =SUM(L2:L32) -> 250490.3 | M33: =SUM(M2:M32) -> 250490.7 | N33: =SUM(N2:N32) -> -0.4 | P33: =SUM(P2:P32) -> 1307050 | Q33: =J33/P33 -> 0.16264489
I34: =I33/G33 -> 0.09378818
M37: =M11+M8+M10 -> 77059.9

Sheet May 25
A1: Sr No | B1: Company/Client Name | C1: GST Number | D1: Contact Detail | E1: Invoice no | F1: Date | G1: Rent Rev | H1: Breakage | I1: Discount on Rent | J1: Net Rev | K1: GST 18% | L1: Gross Rev | M1: Payment Recived | N1: Payment Pending | O1: Payment Type | P1: Purchase unit value | Q1: ROI %
A2: 1 | B2: Sage & Olio | C2: 27ADUFS8750Q1ZQ | E2: 43 | F2: 2nd May | G2: 28670 | H2: 3950 | I2: 5000 | J2: =G2+H2-I2 -> 27620 | K2: =J2*18% -> 4971.6 | L2: =SUM(J2:K2) -> 32591.6 | M2: 32592 | N2: =L2-M2 -> -0.4 | O2: corp account | P2: 174400 | Q2: =J2/P2 -> 0.15837156
A3: 2 | B3: WHOA Mama Hospitality | C3: 27AAEFW0390B1ZF | E3: 44 | F3: 3rd May | G3: 2930 | H3: 0 | I3: 150 | J3: =G3+H3-I3 -> 2780 | K3: =J3*18% -> 500.4 | L3: =SUM(J3:K3) -> 3280.4 | M3: =L3 -> 3280.4 | N3: 0 | O3: corp account | P3: 18700 | Q3: =J3/P3 -> 0.1486631
A4: 3 | B4: Etlior | C4: 27AAGFE2060C1ZY | E4: 45 | F4: 7th May | G4: 26580 | H4: 400 | I4: 0 | J4: =G4+H4-I4 -> 26980 | K4: =J4*18% -> 4856.4 | L4: =SUM(J4:K4) -> 31836.4 | M4: =L4 -> 31836.4 | N4: =L4-M4 -> 0 | O4: corp account | P4: 153900 | Q4: =J4/P4 -> 0.17530864
A5: 4 | B5: Shalimar hotel | C5: 27AABCS7887H1ZS | E5: 46 | F5: 5th May to 10th May | G5: =1470*6 -> 8820 | H5: 0 | I5: 500 | J5: =G5+H5-I5 -> 8320 | K5: =J5*18% -> 1497.6 | L5: =SUM(J5:K5) -> 9817.6 | M5: =L5 -> 9817.6 | N5: 0 | O5: corp account | P5: 11600 | Q5: =J5/P5 -> 0.71724138
A6: 5 | B6: Verve Hospitality | E6: 47 | F6: 45787 | G6: 3150 | H6: 200 | I6: 0 | J6: =G6+H6-I6 -> 3350 | K6: =J6*18% -> 603 | L6: =J6+K6 -> 3953 | M6: 3953 | N6: 0 | O6: corp account | P6: 7000 | Q6: =J6/P6 -> 0.47857143
A7: 4 | B7: Etlior | C7: 27AAGFE2060C1ZY | E7: 48 | F7: 16th May | G7: 81770 | H7: 3570 | I7: 8000 | J7: =G7+H7-I7 -> 77340 | K7: =J7*18% -> 13921.2 | L7: =J7+K7 -> 91261.2 | N7: =L7 -> 91261.2 | O7: corp account | P7: 280000 | Q7: =J7/P7 -> 0.27621429
A8: 5 | B8: Naksha | C8: 27AAKCC4172E1ZP | E8: 49 | F8: 16th May | G8: 8740 | H8: 0 | I8: 0 | J8: =G8+H8-I8 -> 8740 | K8: =J8*18% -> 1573.2 | L8: =J8+K8 -> 10313.2 | M8: =L8 -> 10313.2 | N8: 0 | O8: corp account | P8: 130500 | Q8: =J8/P8 -> 0.06697318
A9: 6 | B9: Foodies Hospitality | C9: 27AAEFF1696H1Z9 | E9: 50 | F9: 27th May | G9: 18720 | H9: 5850 | I9: 0 | J9: =G9+H9-I9 -> 24570 | K9: =J9*18% -> 4422.6 | L9: =J9+K9 -> 28992.6 | N9: =L9 -> 28992.6 | O9: corp account | P9: 149800 | Q9: =J9/P9 -> 0.16401869
A10: 7 | B10: Sage & Saffron | C10: 27ADUFS8750Q1ZQ | E10: 51 | F10: 24th May | G10: 21720 | H10: 1000 | I10: 0 | J10: =G10+H10-I10 -> 22720 | K10: =J10*18% -> 4089.6 | L10: =J10+K10 -> 26809.6 | N10: =L10 -> 26809.6 | O10: corp account | P10: 109320 | Q10: =J10/P10 -> 0.20783022
A11: 8 | B11: GRITTY FOODWORKS PRIVATE LIMITED | C11: 27AAHCG4388B1ZK | E11: 52 | F11: 24th May | G11: 26500 | H11: 3500 | I11: 0 | J11: =G11+H11-I11 -> 30000 | K11: =J11*18% -> 5400 | L11: =J11+K11 -> 35400 | N11: =L11 -> 35400 | O11: corp account | P11: 501900 | Q11: =J11/P11 -> 0.059772863
A12: 10 | B12: Nine Rental | C12: 27AARFN8911G1ZU | E12: 58 | F12: 30th May | G12: 1600 | H12: 0 | I12: 160 | J12: =G12+H12-I12 -> 1440 | K12: =J12*18% -> 259.2 | L12: =SUM(J12:K12) -> 1699.2 | M12: =L12 -> 1699.2 | N12: =L12-M12 -> 0 | O12: corp account | P12: 12000 | Q12: =J12/P12 -> 0.12
A13: 11 | G13: 0 | H13: 0 | I13: 0 | J13: =G13+H13-I13 -> 0 | K13: =J13*18% -> 0 | L13: =J13+K13 -> 0
A14: 12 | G14: 0 | H14: 0 | I14: 0 | J14: =G14+H14-I14 -> 0 | K14: =J14*18% -> 0 | L14: =J14+K14 -> 0
G24: =SUM(G2:G23) -> 229200 | H24: =SUM(H2:H23) -> 18470 | I24: =SUM(I2:I23) -> 13810 | J24: =SUM(J2:J23) -> 233860 | K24: =SUM(K2:K23) -> 42094.8 | L24: =SUM(L2:L23) -> 275954.8 | M24: =SUM(M2:M23) -> 93491.8 | N24: =SUM(N2:N23) -> 182463 | P24: =SUM(P2:P23) -> 1549120 | Q24: =J24/P24 -> 0.15096313
I25: =I24/G24 -> 0.060253054
B31: Products | C31: Rate Per Unit | D31: Units | E31: Total
B32: Charger | C32: 850 | D32: 25 | E32: =C32*D32 -> 21250
B33: Gold mono | C33: 250 | D33: 12 | E33: =C33*D33 -> 3000
B34: Wite side | C34: 350 | D34: 15 | E34: =C34*D34 -> 5250
B35: glass and blue | C35: 350 | D35: 12 | E35: =C35*D35 -> 4200
B36: Brown platter | C36: 750 | D36: 8 | E36: =C36*D36 -> 6000
B37: One bowl / stand for offcie table | C37: 550 | D37: 1 | E37: =C37*D37 -> 550
B38: Total | C38: =SUM(C32:C36) -> 2550 | D38: =SUM(D32:D37) -> 73 | E38: =SUM(E32:E37) -> 40250
B39: GST @18% | E39: =E38*18% -> 7245
B40: Total amt cheque given | E40: =SUM(E38:E39) -> 47495

Sheet June 25
A1: Sr No | B1: Company/Client Name | C1: GST Number | D1: Contact Detail | E1: Invoice no | F1: Date | G1: Rent Rev | H1: Breakage | I1: Discount on Rent | J1: Net Rev | K1: GST 18% | L1: Gross Rev | M1: Payment Recived | N1: Payment Pending | O1: Payment Type | P1: Purchase unit value | Q1: ROI %
A2: 1 | B2: Orta Restaurant Amricano | C2: 27AAHFE1614M1ZE | E2: 53 | F2: 1st | G2: ='[1]Americno 30th May '!$B$3 -> 25820 | H2: 4000 | I2: ='[1]Americno 30th May '!$B$4 -> 2582 | J2: =G2+H2-I2 -> 27238 | K2: =J2*18% -> 4902.84 | L2: =SUM(J2:K2) -> 32140.84 | M2: 0 | N2: =L2-M2 -> 32140.84 | O2: corp account | P2: 190600 | Q2: =J2/P2 -> 0.14290661
A3: 2 | B3: Amal | C3: 27ADUFS8750Q1ZQ | E3: 54 | F3: 1st | G3: 32000 | H3: 0 | I3: =G3*20% -> 6400 | J3: =G3+H3-I3 -> 25600 | K3: =J3*18% -> 4608 | L3: =SUM(J3:K3) -> 30208 | M3: 0 | N3: =L3-M3 -> 30208 | O3: corp account | P3: 272100 | Q3: =J3/P3 -> 0.094083058
A4: 3 | B4: Iteeha Hospitality | C4: 27AAHCI3079B1ZO | E4: 55 | F4: 1st | G4: 8800 | H4: 200 | I4: 0 | J4: =G4+H4-I4 -> 9000 | K4: =J4*18% -> 1620 | L4: =J4+K4 -> 10620 | N4: =L4 -> 10620 | O4: corp account | P4: 46100 | Q4: =J4/P4 -> 0.19522777
A5: 4
A6: 5 | B6: Pooja Hiremath | E6: 57 | F6: 30th | G6: 10800 | I6: 540 | J6: =G6+H6-I6 -> 10260 | K6: =J6*18% -> 1846.8 | L6: =J6+K6 -> 12106.8 | M6: =L6 -> 12106.8 | N6: 0 | O6: corp account | P6: 52800 | Q6: =J6/P6 -> 0.19431818
A7: 7 | G7: 0 | H7: 0 | I7: 0 | J7: =G7+H7-I7 -> 0 | K7: =J7*18% -> 0 | L7: =SUM(J7:K7) -> 0 | M7: 0 | N7: =L7-M7 -> 0 | O7: corp account | P7: 0 | Q7: =J7/P7 -> #DIV/0!
A8: 8 | G8: 0 | H8: 0 | I8: 0 | J8: =G8+H8-I8 -> 0 | K8: =J8*18% -> 0 | L8: =SUM(J8:K8) -> 0 | M8: 0 | N8: =L8-M8 -> 0 | O8: corp account | P8: 0 | Q8: =J8/P8 -> #DIV/0!
A9: 9 | G9: 0 | H9: 0 | I9: 0 | J9: =G9+H9-I9 -> 0 | K9: =J9*18% -> 0 | L9: =SUM(J9:K9) -> 0 | M9: 0 | N9: =L9-M9 -> 0 | O9: corp account | P9: 0 | Q9: =J9/P9 -> #DIV/0!
A10: 10 | G10: 0 | H10: 0 | I10: 0 | J10: =G10+H10-I10 -> 0 | K10: =J10*18% -> 0 | L10: =SUM(J10:K10) -> 0 | M10: 0 | N10: =L10-M10 -> 0 | O10: corp account | P10: 0 | Q10: =J10/P10 -> #DIV/0!
A11: 11 | G11: 0 | H11: 0 | I11: 0 | J11: =G11+H11-I11 -> 0 | K11: =J11*18% -> 0 | L11: =SUM(J11:K11) -> 0 | M11: 0 | N11: =L11-M11 -> 0 | O11: corp account | P11: 0 | Q11: =J11/P11 -> #DIV/0!
A12: 12 | G12: 0 | H12: 0 | I12: 0 | J12: =G12+H12-I12 -> 0 | K12: =J12*18% -> 0 | L12: =SUM(J12:K12) -> 0 | M12: 0 | N12: =L12-M12 -> 0 | O12: corp account | P12: 0 | Q12: =J12/P12 -> #DIV/0!
G13: 0 | H13: 0 | I13: 0 | J13: =G13+H13-I13 -> 0 | K13: =J13*18% -> 0 | L13: =SUM(J13:K13) -> 0 | M13: 0 | N13: =L13-M13 -> 0 | P13: 0 | Q13: =J13/P13 -> #DIV/0!
G14: 0 | H14: 0 | I14: 0 | J14: =G14+H14-I14 -> 0 | K14: =J14*18% -> 0 | L14: =SUM(J14:K14) -> 0 | M14: 0 | N14: =L14-M14 -> 0 | P14: 0
G15: 0 | H15: 0 | I15: 0 | J15: =G15+H15-I15 -> 0 | K15: =J15*18% -> 0 | L15: =SUM(J15:K15) -> 0 | M15: 0 | N15: =L15-M15 -> 0 | P15: 0
G16: 0 | H16: 0 | I16: 0 | J16: =G16+H16-I16 -> 0 | K16: =J16*18% -> 0 | L16: =SUM(J16:K16) -> 0 | M16: 0 | N16: =L16-M16 -> 0 | P16: 0
G17: 0 | H17: 0 | I17: 0 | J17: =G17+H17-I17 -> 0 | K17: =J17*18% -> 0 | L17: =SUM(J17:K17) -> 0 | M17: 0 | N17: =L17-M17 -> 0 | P17: 0
G18: 0 | H18: 0 | I18: 0 | J18: =G18+H18-I18 -> 0 | K18: =J18*18% -> 0 | L18: =SUM(J18:K18) -> 0 | M18: 0 | N18: =L18-M18 -> 0 | P18: 0
G19: 0 | H19: 0 | I19: 0 | J19: =G19+H19-I19 -> 0 | K19: =J19*18% -> 0 | L19: =SUM(J19:K19) -> 0 | M19: 0 | N19: =L19-M19 -> 0 | P19: 0
G20: 0 | H20: 0 | I20: 0 | J20: =G20+H20-I20 -> 0 | K20: =J20*18% -> 0 | L20: =SUM(J20:K20) -> 0 | M20: 0 | N20: =L20-M20 -> 0 | P20: 0
G21: 0 | H21: 0 | I21: 0 | J21: =G21+H21-I21 -> 0 | K21: =J21*18% -> 0 | L21: =SUM(J21:K21) -> 0 | M21: 0 | N21: =L21-M21 -> 0 | P21: 0
G22: 0 | H22: 0 | I22: 0 | J22: =G22+H22-I22 -> 0 | K22: =J22*18% -> 0 | L22: =SUM(J22:K22) -> 0 | M22: 0 | N22: =L22-M22 -> 0 | P22: 0
G23: 0 | H23: 0 | I23: 0 | J23: =G23+H23-I23 -> 0 | K23: =J23*18% -> 0 | L23: =SUM(J23:K23) -> 0 | M23: 0 | N23: =L23-M23 -> 0 | P23: 0
G24: 0 | H24: 0 | I24: 0 | J24: =G24+H24-I24 -> 0 | K24: =J24*18% -> 0 | L24: =SUM(J24:K24) -> 0 | M24: 0 | N24: =L24-M24 -> 0 | P24: 0
G26: =SUM(G2:G25) -> 77420 | H26: 1 | I26: =SUM(I2:I25) -> 9522 | J26: =SUM(J2:J25) -> 72098 | K26: =SUM(K2:K25) -> 12977.64 | L26: =SUM(L2:L25) -> 85075.64 | M26: =SUM(M2:M25) -> 12106.8 | N26: =SUM(N2:N25) -> 72968.84 | P26: =SUM(P2:P25) -> 561600 | Q26: =J26/P26 -> 0.12837963
I27: =I26/G26 -> 0.12299148
